pd_cli/__init__.py
pd_cli/build.py
pd_cli/deploy.py
pd_cli/exceptions.py
pd_cli/helpers.py
pd_cli/main.py
pd_cli/run.py
pd_cli-1.1.0.dist-info/entry_points.txt
pd_cli-1.1.0.dist-info/LICENSE
pd_cli-1.1.0.dist-info/WHEEL
pd_cli-1.1.0.dist-info/METADATA
pd_cli-1.1.0.dist-info/RECORD
