Metadata-Version: 2.1
Name: pd-cli
Version: 1.1.0
Summary: CLI for https://pythondeploy.co/.
Home-page: https://github.com/pythondeploy/cli
License: BSD-3-Clause
Author: Federico Jaramillo Martínez
Author-email: federicojaramillom@gmail.com
Requires-Python: >=3.7,<4.0
Classifier: License :: OSI Approved :: BSD License
Classifier: Programming Language :: Python :: 3
Classifier: Programming Language :: Python :: 3.10
Classifier: Programming Language :: Python :: 3.7
Classifier: Programming Language :: Python :: 3.8
Classifier: Programming Language :: Python :: 3.9
Requires-Dist: boto3 (>=1.20.5,<2.0.0)
Requires-Dist: docker (>=5.0.3,<6.0.0)
Requires-Dist: typer (>=0.4.0,<0.5.0)
